README.md
setup.cfg
setup.py
ESP/DeviceList.py.sample
ESP/__init__.py
ESP/conf/Baro.py
ESP/conf/Cellar.py
ESP/conf/Config.py.sample
ESP/conf/Dimmer.py
ESP/conf/Garage.py
ESP/conf/Neo.py
ESP/conf/NeoClock.py
ESP/conf/Newbie.py
ESP/conf/Noise.py
ESP/conf/SimpleIO.py
ESP/conf/SimpleIO2.py
ESP/conf/__init__.py
ESP/handlers/AnalogIn.py
ESP/handlers/DS18B20.py
ESP/handlers/DigitalIn.py
ESP/handlers/DigitalOut.py
ESP/handlers/DigitalPulse.py
ESP/handlers/Interrupt.py
ESP/handlers/NeoGen.py
ESP/handlers/NoiseDetect.py
ESP/handlers/Oled.py
ESP/handlers/Pressure.py
ESP/handlers/PwmOut.py
ESP/handlers/Xpad.py
ESP/handlers/__init__.py
ESP/rt/BaseHandler.py
ESP/rt/LogNone.py
ESP/rt/LogToFile.py
ESP/rt/Runtime.py
ESP/rt/WifiHotspot.py
ESP/rt/WifiScan.py
ESP/rt/__init__.py
ESP/rt/main.py
ESP/rt/mqtt.py
ESP/var/NeoClock.py
ESP/var/NeoFile.py
ESP/var/NeoRun.py
ESP/var/__init__.py
Espynoza/EspyConfig.py.sample
Espynoza/EspyListen.py
Espynoza/EspySQL.py
Espynoza/Espynoza.py
Espynoza/__init__.py
Espynoza.egg-info/PKG-INFO
Espynoza.egg-info/SOURCES.txt
Espynoza.egg-info/dependency_links.txt
Espynoza.egg-info/entry_points.txt
Espynoza.egg-info/requires.txt
Espynoza.egg-info/top_level.txt