Metadata-Version: 1.2
Name: Espynoza
Version: 0.2.5
Summary: Runtime and upload utilities for MicroPython/ESP8266 boards
Home-page: https://github.com/finalstate/Espynoza
Author: René Schmit
Author-email: rene.schmit@plaakert.lu
License: MIT
Keywords: IoT esp8266 MicroPython runtime uploader MQTT OverTheAir
Platform: UNKNOWN
Classifier: Development Status :: 3 - Alpha
Classifier: Intended Audience :: Developers
Classifier: Topic :: Software Development :: Build Tools
Classifier: License :: OSI Approved :: MIT License
Classifier: Programming Language :: Python :: 3
Classifier: Programming Language :: Python :: 3.6
Requires-Python: >=3.6
